e3fp/__init__.py
e3fp/pipeline.py
e3fp/util.py
e3fp/config/__init__.py
e3fp/config/defaults.cfg
e3fp/config/params.py
e3fp/conformer/__init__.py
e3fp/conformer/generate.py
e3fp/conformer/generator.py
e3fp/conformer/protonation.py
e3fp/conformer/util.py
e3fp/fingerprint/__init__.py
e3fp/fingerprint/array_ops.py
e3fp/fingerprint/db.py
e3fp/fingerprint/fprint.py
e3fp/fingerprint/fprinter.py
e3fp/fingerprint/generate.py
e3fp/fingerprint/structs.py
e3fp/fingerprint/util.py
e3fp/fingerprint/metrics/__init__.py
e3fp/fingerprint/metrics/array_metrics.py
e3fp/fingerprint/metrics/fprint_metrics.py
e3fp-1.2.7.dist-info/entry_points.txt
e3fp-1.2.7.dist-info/LICENSE.txt
e3fp-1.2.7.dist-info/WHEEL
e3fp-1.2.7.dist-info/METADATA
e3fp-1.2.7.dist-info/RECORD
