Metadata-Version: 2.3
Name: e3fp
Version: 1.2.7
Summary: Molecular 3D fingerprinting
Keywords: e3fp,3d,molecule,fingerprint,conformer
Author-email: Seth Axen <seth.axen@gmail.com>
Requires-Python: >=3.9, <3.14
Classifier: Programming Language :: Python
Classifier: Programming Language :: Python :: 3.9
Classifier: Programming Language :: Python :: 3.10
Classifier: Programming Language :: Python :: 3.11
Classifier: Programming Language :: Python :: 3.12
Classifier: Programming Language :: Python :: 3.13
Classifier: License :: OSI Approved :: GNU Lesser General Public License v3 (LGPLv3)
Classifier: Operating System :: OS Independent
Classifier: Development Status :: 4 - Beta
Classifier: Intended Audience :: Science/Research
Classifier: Intended Audience :: Developers
Classifier: Topic :: Scientific/Engineering :: Chemistry
Classifier: Topic :: Software Development :: Libraries :: Python Modules
Requires-Dist: mmh3>=2.3.1
Requires-Dist: numpy>=1.11.3
Requires-Dist: rdkit>=2016.03.4
Requires-Dist: scipy>=0.18.0
Requires-Dist: sdaxen_python_utilities>=0.1.5
Requires-Dist: smart_open>=1.8.3
Requires-Dist: e3fp[docs] ; extra == "dev"
Requires-Dist: e3fp[test] ; extra == "dev"
Requires-Dist: sphinx ; extra == "docs"
Requires-Dist: sphinxcontrib-programoutput ; extra == "docs"
Requires-Dist: sphinx-rtd-theme ; extra == "docs"
Requires-Dist: h5py ; extra == "optional"
Requires-Dist: mpi4py ; extra == "optional"
Requires-Dist: numba ; extra == "optional"
Requires-Dist: six ; extra == "optional"
Requires-Dist: standardiser ; extra == "optional"
Requires-Dist: mock ; extra == "test"
Requires-Dist: pytest ; extra == "test"
Requires-Dist: pytest-cov ; extra == "test"
Requires-Dist: e3fp[optional] ; extra == "test"
Project-URL: Download, https://github.com/keiserlab/e3fp/tarball/{version}
Project-URL: Homepage, https://github.com/keiserlab/e3fp
Provides-Extra: dev
Provides-Extra: docs
Provides-Extra: optional
Provides-Extra: test
